CHANGES.txt
MANIFEST.in
README.rst
setup.py
isotoma/__init__.py
isotoma.recipe.buildbot.egg-info/PKG-INFO
isotoma.recipe.buildbot.egg-info/SOURCES.txt
isotoma.recipe.buildbot.egg-info/dependency_links.txt
isotoma.recipe.buildbot.egg-info/entry_points.txt
isotoma.recipe.buildbot.egg-info/namespace_packages.txt
isotoma.recipe.buildbot.egg-info/not-zip-safe
isotoma.recipe.buildbot.egg-info/requires.txt
isotoma.recipe.buildbot.egg-info/top_level.txt
isotoma/recipe/__init__.py
isotoma/recipe/buildbot/__init__.py
isotoma/recipe/buildbot/buildbot.tac
isotoma/recipe/buildbot/master.cfg
isotoma/recipe/buildbot/runner.py
isotoma/recipe/buildbot/slaverunner.py
isotoma/recipe/buildbot/support.py
isotoma/recipe/buildbot/upgrader.py