Metadata-Version: 1.1
Name: isotoma.recipe.buildbot
Version: 0.0.33
Summary: A recipe to help setup a buildbot master and slaves
Home-page: UNKNOWN
Author: John Carr
Author-email: john.carr@isotoma.com
License: Apache Software License
Keywords: buildout buildbot template
Platform: UNKNOWN
Classifier: Framework :: Buildout
Classifier: Intended Audience :: System Administrators
Classifier: Operating System :: POSIX
Classifier: License :: OSI Approved :: Apache Software License
